pyconduit/__init__.py
pyconduit/block.py
pyconduit/category.py
pyconduit/collection.py
pyconduit/conduit.py
pyconduit/enums.py
pyconduit/other.py
pyconduit/step.py
pyconduit/utils.py
pyconduit/categories/__init__.py
pyconduit/categories/dictionary.py
pyconduit/categories/lists.py
pyconduit/categories/logic.py
pyconduit/categories/math.py
pyconduit/categories/object.py
pyconduit/categories/text.py
pyconduit/categories/variable.py
pyconduit-1.0.4.dist-info/LICENSE.md
pyconduit-1.0.4.dist-info/METADATA
pyconduit-1.0.4.dist-info/WHEEL
pyconduit-1.0.4.dist-info/top_level.txt
pyconduit-1.0.4.dist-info/RECORD
