Metadata-Version: 2.1
Name: pyconduit
Version: 1.0.4
Summary: A simple workflow manager that can execute developer-defined methods from user-defined workflow files.
Home-page: https://github.com/ysfchn/pyconduit
Author: ysfchn
License: MIT
Project-URL: Documentation, https://pyconduit.ysfchn.com/
Platform: UNKNOWN
Classifier: Programming Language :: Python :: 3.7
Classifier: License :: OSI Approved :: MIT License
Classifier: Operating System :: OS Independent
Requires-Python: >=3.7
License-File: LICENSE.md
Requires-Dist: wrapt
Requires-Dist: typing-extensions
Provides-Extra: all
Requires-Dist: pydantic (>=1.7) ; extra == 'all'
